dkron/__init__.py
dkron/__main__.py
dkron/api.py
dkron/cli.py
dkron-0.0.5.dist-info/DESCRIPTION.rst
dkron-0.0.5.dist-info/METADATA
dkron-0.0.5.dist-info/RECORD
dkron-0.0.5.dist-info/WHEEL
dkron-0.0.5.dist-info/entry_points.txt
dkron-0.0.5.dist-info/metadata.json
dkron-0.0.5.dist-info/top_level.txt
