Metadata-Version: 2.0
Name: dkron
Version: 0.0.5
Summary: Command line interface client and python library for Dkron
Home-page: https://github.com/Eyjafjallajokull/dkron-python
Author: Pawel Olejniczak
Author-email: pawel.olejniczak@gmail.com
License: MIT
Download-URL: https://github.com/Eyjafjallajokull/dkron-python/tarball/0.0.5
Platform: UNKNOWN
Classifier: Development Status :: 3 - Alpha
Classifier: Intended Audience :: Information Technology
Classifier: Programming Language :: Python :: 3
Classifier: Environment :: Console
Classifier: Topic :: System :: Clustering
Classifier: Topic :: System :: Distributed Computing
Requires-Dist: appdirs (==1.4.0)
Requires-Dist: click (==6.7)
Requires-Dist: packaging (==16.8)
Requires-Dist: pyparsing (==2.1.10)
Requires-Dist: requests (==2.13.0)
Requires-Dist: six (==1.10.0)
